<?xml version="1.0" encoding="utf-8"?>
<CapabilityStatement xmlns="http://hl7.org/fhir" xmlns:xsi="http://www.w3.org/2001/XMLSchema-instance">
  <id value="exchange-routing-intermediary" />
  <url value="http://hl7.org/fhir/us/exchange-routing/CapabilityStatement/exchange-routing-intermediary" />
  <version value="0.1.0" />
  <name value="ExchangeRoutingIntermediaryCapabilityStatement" />
  <title value="Exchange Routing Intermediary Capability Statement" />
  <status value="active" />
  <experimental value="false" />
  <date value="2021-07-20T00:00:00-05:00" />
  <publisher value="HL7 International - FHIR Infrastructure" />
  <description value="This CapabilityStatement describes the expected capabilities of an intermediary server that conforms to the conventions of the Hybrid / Intermediary Exchange FHIR implementation guide." />
  <jurisdiction>
    <coding>
      <system value="urn:iso:std:iso:3166" />
      <code value="US" />
      <display value="United States of America" />
    </coding>
  </jurisdiction>
  <kind value="requirements" />
  <fhirVersion value="4.0.1" />
  <format value="xml" />
  <format value="json" />
  <patchFormat value="application/json-patch+json" />
  <implementationGuide value="http://hl7.org/fhir/us/exchange-routing/ImplementationGuide/exchange-routing" />
  <rest>
    <mode value="server" />
    <documentation value="When participating in exchanges described in the Hybrid / Intermediary FHIR IG, the intermediary server **SHALL** pass FHIR resources returned by the destination server to the originator unchanged. 1. Implement RESTful behavior according to the FHIR specification. 1. Support the JSON source format. &#xA;When participating in exchanges described in the Hybrid / Intermediary FHIR IG, the intermediary server, the intermediary server **SHOULD**: 1. Support the XML source format." />
    <security>
      <description value="The intermediary server SHALL implement Transport Layer Security (TLS) for all exchanges covered in this IG. &#xA;1. Security tokens generated by the destination for use by the originator SHALL be forwarded by the intermediary server to the originating client. &#xA;1. The intermediary server MAY implement the [HL7 / UDAP Security for Scalable Registration, Authentication, and Authorization FHIR Implementation Guide](http://hl7.org/fhir/us/udap-security/2021Sep). 1. For general security considerations refer to [FHIR Security and Privacy Considerations](https://www.hl7.org/fhir/secpriv-module.html). &#xA;1. For additional security guidance, refer to the [core FHIR Security guidance page](https://www.hl7.org/fhir/security.html)." />
    </security>
  </rest>
</CapabilityStatement>